maixpy_ui/__init__.py
maixpy_ui/components/__init__.py
maixpy_ui/components/button.py
maixpy_ui/components/checkbox.py
maixpy_ui/components/radio.py
maixpy_ui/components/slider.py
maixpy_ui/components/switch.py
maixpy_ui/core/__init__.py
maixpy_ui/core/resolution_adapter.py
maixpy_ui/core/ui_manager.py
maixpy_ui_lib-2.4.dist-info/METADATA
maixpy_ui_lib-2.4.dist-info/WHEEL
maixpy_ui_lib-2.4.dist-info/licenses/LICENSE
maixpy_ui_lib-2.4.dist-info/RECORD
