Metadata-Version: 2.4
Name: maixpy-ui-lib
Version: 2.4
Summary: A lightweight UI component library for MaixPy.
Project-URL: Homepage, https://github.com/aristorechina/MaixPy-UI-Lib/
Project-URL: Repository, https://github.com/aristorechina/MaixPy-UI-Lib/
Project-URL: Bug Tracker, https://github.com/aristorechina/MaixPy-UI-Lib/issues
Author: Aristore, levi_jia, HYKMAX
License-Expression: Apache-2.0
License-File: LICENSE
Keywords: embedded,gui,maixpy,micropython,ui
Classifier: Development Status :: 4 - Beta
Classifier: Intended Audience :: Developers
Classifier: License :: OSI Approved :: Apache Software License
Classifier: Operating System :: OS Independent
Classifier: Programming Language :: Python :: 3
Classifier: Topic :: Software Development :: Embedded Systems
Classifier: Topic :: Software Development :: Libraries :: Python Modules
Requires-Python: >=3.8
Requires-Dist: maixpy
